{
  "info": {
    "_testmasterhub_id": "66295408-47c4-4c11-beed-b51fdf2fa1f7",
    "name": "JSON Placeholder",
    "description": "This is a new collection",
    "schema": "https://schema.gettmh.com/json/collection/v2.1.0/collection.json",
    "_exporter_id": "ded29c9a-c3fd-41ac-8ab6-1eab672b670f"
  },
  "item": [
    {
      "name": "Req 1",
      "event": [
        {
          "listen": "test",
          "script": {
            "exec": [],
            "type": "text/javascript",
            "packages": {}
          }
        },
        {
          "listen": "prerequest",
          "script": {
            "exec": [],
            "type": "text/javascript",
            "packages": {}
          }
        }
      ],
      "request": {
        "method": "GET",
        "header": [
          {
            "key": "Accept-Encoding",
            "value": "gzip, deflate, br"
          },
          {
            "key": "User-Agent",
            "value": "TestMasterHub/1.0 (Windows NT 10.0; Win64; x64)"
          },
          {
            "key": "Accept",
            "value": "application/json"
          },
          {
            "key": "Connection",
            "value": "keep-alive"
          }
        ],
        "auth": {
          "type": "bearer",
          "bearer": [
            {
              "key": "token",
              "value": "",
              "type": "string"
            }
          ]
        },
        "url": {
          "raw": "{{URL}}/posts",
          "host": [],
          "path": []
        },
        "body": {
          "mode": "raw",
          "raw": "",
          "options": {
            "raw": {
              "language": "json"
            }
          }
        }
      },
      "response": [],
      "id": "770738ad-b218-40e3-8c97-ad5f6ae18c84"
    },
    {
      "name": "Req 2",
      "event": [
        {
          "listen": "test",
          "script": {
            "exec": [],
            "type": "text/javascript",
            "packages": {}
          }
        },
        {
          "listen": "prerequest",
          "script": {
            "exec": [],
            "type": "text/javascript",
            "packages": {}
          }
        }
      ],
      "request": {
        "method": "GET",
        "header": [
          {
            "key": "Accept-Encoding",
            "value": "gzip, deflate, br"
          },
          {
            "key": "User-Agent",
            "value": "TestMasterHub/1.0 (Windows NT 10.0; Win64; x64)"
          },
          {
            "key": "Accept",
            "value": "application/json"
          },
          {
            "key": "Connection",
            "value": "keep-alive"
          }
        ],
        "auth": {
          "type": "bearer",
          "bearer": [
            {
              "key": "token",
              "value": "",
              "type": "string"
            }
          ]
        },
        "url": {
          "raw": "{{URL}}/posts/1",
          "host": [],
          "path": []
        },
        "body": {
          "mode": "raw",
          "raw": "",
          "options": {
            "raw": {
              "language": "json"
            }
          }
        }
      },
      "response": [],
      "id": "b1da0848-c7b6-47ce-9dce-007aa696dbe1"
    },
    {
      "name": "Req 3",
      "event": [
        {
          "listen": "test",
          "script": {
            "exec": [],
            "type": "text/javascript",
            "packages": {}
          }
        },
        {
          "listen": "prerequest",
          "script": {
            "exec": [],
            "type": "text/javascript",
            "packages": {}
          }
        }
      ],
      "request": {
        "method": "GET",
        "header": [
          {
            "key": "Accept-Encoding",
            "value": "gzip, deflate, br"
          },
          {
            "key": "User-Agent",
            "value": "TestMasterHub/1.0 (Windows NT 10.0; Win64; x64)"
          },
          {
            "key": "Accept",
            "value": "application/json"
          },
          {
            "key": "Connection",
            "value": "keep-alive"
          }
        ],
        "auth": {
          "type": "bearer",
          "bearer": [
            {
              "key": "token",
              "value": "",
              "type": "string"
            }
          ]
        },
        "url": {
          "raw": "{{URL}}/posts/1/comments",
          "host": [],
          "path": []
        },
        "body": {
          "mode": "raw",
          "raw": "",
          "options": {
            "raw": {
              "language": "json"
            }
          }
        }
      },
      "response": [],
      "id": "4f58f5a2-0f36-4014-bbfb-e773797551b3"
    },
    {
      "name": "Request 5",
      "event": [
        {
          "listen": "test",
          "script": {
            "exec": [],
            "type": "text/javascript",
            "packages": {}
          }
        },
        {
          "listen": "prerequest",
          "script": {
            "exec": [],
            "type": "text/javascript",
            "packages": {}
          }
        }
      ],
      "request": {
        "method": "GET",
        "header": [
          {
            "key": "Accept-Encoding",
            "value": "gzip, deflate, br"
          },
          {
            "key": "User-Agent",
            "value": "TestMasterHub/1.0 (Windows NT 10.0; Win64; x64)"
          },
          {
            "key": "Accept",
            "value": "application/json"
          },
          {
            "key": "Connection",
            "value": "keep-alive"
          }
        ],
        "auth": {
          "type": "none"
        },
        "url": {
          "raw": "{{URL}}/comments?postId=1",
          "host": [],
          "path": []
        },
        "body": {
          "mode": "raw",
          "raw": "",
          "options": {
            "raw": {
              "language": "json"
            }
          }
        }
      },
      "response": [],
      "id": "d1ac2ea7-3a0a-476f-b91e-81cf58c1eb92"
    },
    {
      "name": "Req 4",
      "event": [
        {
          "listen": "test",
          "script": {
            "exec": [],
            "type": "text/javascript",
            "packages": {}
          }
        },
        {
          "listen": "prerequest",
          "script": {
            "exec": [],
            "type": "text/javascript",
            "packages": {}
          }
        }
      ],
      "request": {
        "method": "GET",
        "header": [
          {
            "key": "Accept-Encoding",
            "value": "gzip, deflate, br"
          },
          {
            "key": "User-Agent",
            "value": "TestMasterHub/1.0 (Windows NT 10.0; Win64; x64)"
          },
          {
            "key": "Accept",
            "value": "application/json"
          },
          {
            "key": "Connection",
            "value": "keep-alive"
          }
        ],
        "auth": {
          "type": "bearer",
          "bearer": [
            {
              "key": "token",
              "value": "",
              "type": "string"
            }
          ]
        },
        "url": {
          "raw": "https://dummyjson.com/users",
          "host": [
            "dummyjson",
            "com"
          ],
          "path": [
            "users"
          ]
        },
        "body": {
          "mode": "raw",
          "raw": "",
          "options": {
            "raw": {
              "language": "json"
            }
          }
        }
      },
      "response": [],
      "id": "7612e4cb-94c4-4bb9-85e9-6610619df2cb"
    },
    {
      "name": "Request 7",
      "event": [
        {
          "listen": "test",
          "script": {
            "exec": [],
            "type": "text/javascript",
            "packages": {}
          }
        },
        {
          "listen": "prerequest",
          "script": {
            "exec": [],
            "type": "text/javascript",
            "packages": {}
          }
        }
      ],
      "request": {
        "method": "GET",
        "header": [
          {
            "key": "Accept-Encoding",
            "value": "gzip, deflate, br"
          },
          {
            "key": "User-Agent",
            "value": "TestMasterHub/1.0 (Windows NT 10.0; Win64; x64)"
          },
          {
            "key": "Accept",
            "value": "application/json"
          },
          {
            "key": "Connection",
            "value": "keep-alive"
          }
        ],
        "auth": {
          "type": "none"
        },
        "url": {
          "raw": "https://dummyjson.com/todos",
          "host": [
            "dummyjson",
            "com"
          ],
          "path": [
            "todos"
          ]
        },
        "body": {
          "mode": "raw",
          "raw": "",
          "options": {
            "raw": {
              "language": "json"
            }
          }
        }
      },
      "response": [],
      "id": "ea8cc673-3693-4109-a2e9-f6a6542185ab"
    },
    {
      "name": "Req 6",
      "event": [
        {
          "listen": "test",
          "script": {
            "exec": [],
            "type": "text/javascript",
            "packages": {}
          }
        },
        {
          "listen": "prerequest",
          "script": {
            "exec": [],
            "type": "text/javascript",
            "packages": {}
          }
        }
      ],
      "request": {
        "method": "POST",
        "header": [
          {
            "key": "Accept-Encoding",
            "value": "gzip, deflate, br"
          },
          {
            "key": "User-Agent",
            "value": "TestMasterHub/1.0 (Windows NT 10.0; Win64; x64)"
          },
          {
            "key": "Accept",
            "value": "application/json"
          },
          {
            "key": "Connection",
            "value": "keep-alive"
          }
        ],
        "auth": {
          "type": "bearer",
          "bearer": [
            {
              "key": "token",
              "value": "",
              "type": "string"
            }
          ]
        },
        "url": {
          "raw": "{{URL}}/posts",
          "host": [],
          "path": []
        },
        "body": {
          "mode": "raw",
          "raw": "",
          "options": {
            "raw": {
              "language": "json"
            }
          }
        }
      },
      "response": [],
      "id": "3afefd35-11f7-4fd7-8c06-f41593ff4974"
    },
    {
      "name": "Request 9",
      "event": [
        {
          "listen": "test",
          "script": {
            "exec": [],
            "type": "text/javascript",
            "packages": {}
          }
        },
        {
          "listen": "prerequest",
          "script": {
            "exec": [],
            "type": "text/javascript",
            "packages": {}
          }
        }
      ],
      "request": {
        "method": "DELETE",
        "header": [
          {
            "key": "Accept-Encoding",
            "value": "gzip, deflate, br"
          },
          {
            "key": "User-Agent",
            "value": "TestMasterHub/1.0 (Windows NT 10.0; Win64; x64)"
          },
          {
            "key": "Accept",
            "value": "application/json"
          },
          {
            "key": "Connection",
            "value": "keep-alive"
          }
        ],
        "auth": {
          "type": "none"
        },
        "url": {
          "raw": "{{URL}}/posts/1",
          "host": [],
          "path": []
        },
        "body": {
          "mode": "raw",
          "raw": "",
          "options": {
            "raw": {
              "language": "json"
            }
          }
        }
      },
      "response": [],
      "id": "30ec9299-aaf9-46b9-bd50-1fd7348c94f8"
    },
    {
      "id": "14b54849-c917-4802-8469-6e0946bcf26a",
      "name": "test req",
      "requestMode": "rest",
      "response": [],
      "data": {
        "isran": false
      },
      "auth": {
        "type": "basic",
        "basic": [
          {
            "key": "password",
            "value": "admin",
            "type": "string"
          },
          {
            "key": "username",
            "value": "admin",
            "type": "string"
          }
        ]
      },
      "variable": [
        {
          "key": "dummy",
          "value": "123",
          "type": "string"
        }
      ],
      "event": [
        {
          "listen": "test",
          "script": {
            "exec": [],
            "type": "text/javascript",
            "packages": {}
          }
        },
        {
          "listen": "prerequest",
          "script": {
            "exec": [],
            "type": "text/javascript",
            "packages": {}
          }
        }
      ],
      "request": {
        "method": "GET",
        "header": [
          {
            "key": "Accept-Encoding",
            "value": "gzip, deflate, br"
          },
          {
            "key": "User-Agent",
            "value": "TestMasterHub/1.0 (Windows NT 10.0; Win64; x64)"
          },
          {
            "key": "Accept",
            "value": "application/json"
          },
          {
            "key": "Connection",
            "value": "keep-alive"
          }
        ],
        "auth": {
          "type": "bearer",
          "bearer": [
            {
              "key": "token",
              "value": "",
              "type": "string"
            }
          ]
        },
        "url": {
          "raw": "https://jsonplaceholder.typicode.com/users",
          "protocol": "https",
          "host": [
            "jsonplaceholder",
            "typicode",
            "com"
          ],
          "path": [
            "users"
          ],
          "variable": [],
          "query": []
        },
        "body": {
          "mode": "raw",
          "raw": "",
          "options": {
            "raw": {
              "language": "json"
            }
          }
        }
      }
    }
  ],
  "auth": {
    "type": "noauth",
    "basic": [
      {
        "key": "username",
        "value": "",
        "type": "string"
      },
      {
        "key": "password",
        "value": "",
        "type": "string"
      }
    ]
  },
  "event": [
    {
      "listen": "prerequest",
      "script": {
        "type": "text/javascript",
        "packages": {},
        "exec": [
          ""
        ]
      }
    },
    {
      "listen": "test",
      "script": {
        "type": "text/javascript",
        "packages": {},
        "exec": [
          "tmh"
        ]
      }
    }
  ],
  "variable": [],
  "id": "66295408-47c4-4c11-beed-b51fdf2fa1f7"
}